MANIFEST.in
README.rst
license_reference.txt
setup.cfg
setup.py
Opy.egg-info/PKG-INFO
Opy.egg-info/SOURCES.txt
Opy.egg-info/dependency_links.txt
Opy.egg-info/top_level.txt
opy/opy.py
opy/opy_config.txt
tests/dog_walker/bosses.py
tests/dog_walker/dog_walker.py
tests/dog_walker/dogs.py
tests/dog_walker/func_walker.py
tests/dog_walker/poly_walker_test.py
tests/dog_walker/this_is_a_test_dummy_and_nothing_else.py
tests/fixes/fix_issue_17/main.py
tests/fixes/fix_issue_17/opy_config.txt
tests/fixes/fix_issue_17_opy/main.py