Metadata-Version: 1.1
Name: Opy
Version: 1.1.28
Summary: OPY - Obfuscator for Python, string obfuscation added, keyword added
Home-page: https://github.com/JdeH/Opy/
Author: Jacques de Hooge
Author-email: jacques.de.hooge@qquick.org
License: Apache 2
Keywords: opy,obfuscator,obfuscation,obfuscate,kivy,pyo,python
Platform: UNKNOWN
Classifier: Development Status :: 5 - Production/Stable
Classifier: Intended Audience :: Developers
Classifier: Natural Language :: English
Classifier: License :: Other/Proprietary License
Classifier: Topic :: Software Development :: Libraries :: Python Modules
Classifier: Operating System :: OS Independent
Classifier: Programming Language :: Python :: 2.7
Classifier: Programming Language :: Python :: 3
